MANIFEST.in
README.md
setup.cfg
setup.py
jydwdc/__init__.py
jydwdc/wdc.py
jydwdc.egg-info/PKG-INFO
jydwdc.egg-info/SOURCES.txt
jydwdc.egg-info/dependency_links.txt
jydwdc.egg-info/entry_points.txt
jydwdc.egg-info/top_level.txt