Metadata-Version: 1.0
Name: jydwdc
Version: 0.8
Summary: this is a demo
Home-page: UNKNOWN
Author: jiangyd
Author-email: 962584902@qq.com
License: MIT License
Keywords: jydwdc
Platform: any
